link_reaper/__init__.py
link_reaper/link_collector.py
link_reaper/link_info.py
link_reaper/reaper.py
link_reaper/tests/test_cli.py
link_reaper/tests/test_link_funcs.py
the_link_reaper-0.8.3.dist-info/LICENSE
the_link_reaper-0.8.3.dist-info/METADATA
the_link_reaper-0.8.3.dist-info/WHEEL
the_link_reaper-0.8.3.dist-info/entry_points.txt
the_link_reaper-0.8.3.dist-info/top_level.txt
the_link_reaper-0.8.3.dist-info/RECORD
