Metadata-Version: 2.2
Name: the_link_reaper
Version: 0.8.3
Summary: Removes dead & duplicate links from markdown files and updates redirects.
Author-email: Ibrahim S <ibrahimisprogramming@gmail.com>
License: MIT License
Project-URL: Repository, https://github.com/sharktrexer/link-reaper
Project-URL: Issues, https://github.com/sharktrexer/link-reaper/issues
Keywords: markdown,links,list cleaning,cli,urls
Classifier: Development Status :: 4 - Beta
Classifier: Programming Language :: Python :: 3
Classifier: License :: OSI Approved :: MIT License
Classifier: Operating System :: OS Independent
Requires-Python: >=3.9.6
License-File: LICENSE
Requires-Dist: requests
Requires-Dist: Click
